Workbook

Sheet 0. Borrower Profile
A1: SLL STRUCTURING MODEL — ALBION INDUSTRIALS PLC (HYPOTHETICAL)
A3: Fictional entity, for illustrative purposes only. No real company financial data is used anywhere in this model. All targets, rates and costs are illustrative.
A6: Attribute | B6: Value
A7: Sector | B7: UK Heavy Industrials (Steel & Construction Materials)
A8: Revenue (hypothetical) | B8: £2.8bn
A9: EBITDA margin (hypothetical) | B9: 11%
A10: Existing debt (hypothetical) | B10: £650m revolving credit facility
A11: Credit rating (hypothetical) | B11: BBB– (investment grade)
A12: Scope 1+2 intensity (baseline) | B12: 310 tCO2e per £m revenue
A13: Renewable energy share (baseline) | B13: 18%
A14: Reference framework | B14: LMA/APLMA/LSTA Sustainability-Linked Loan Principles (2023 edition; revised March 2025)
A16: HOW TO USE THIS WORKBOOK
A17: Yellow cells are inputs; everything else is a live formula. Sheet 1 tracks KPI progress. Sheet 2 sets illustrative SPTs and derives linear glide paths for all three KPIs. Sheet 3 prices the facility — the number of SPTs met is a separate input there, not driven by Sheet 1. Sheet 4 shows how the ratchet benefit varies with drawdown, and Sheet 5 compares the facility with an equivalent conventional revolver.
A22: REPRODUCIBILITY
A23: This workbook is generated by scripts/build_model.py from the calculations in scripts/sll.py — it is not hand-maintained. Rebuild it with: python scripts/build_model.py

Sheet 1. KPI Tracker
A1: KPI TRACKER — BASELINE VS CURRENT VS TARGET
A3: KPI | B3: Metric | C3: Baseline (2024) | D3: Current (2026, hypothetical) | E3: Target / SPT | F3: Progress to target | G3: Target year
A4: Carbon intensity | B4: tCO2e per £m revenue (Scope 1+2) | C4: 310 | D4: 267 | E4: 217 | F4: =(D4-C4)/(E4-C4) | G4: 2028
A5: Renewable energy share | B5: % of electricity from renewables | C5: 18 | D5: 34 | E5: 60 | F5: =(D5-C5)/(E5-C5) | G5: 2028
A6: Supply chain audit coverage | B6: % tier-1 suppliers audited to ESG standards | C6: 35 | D6: 52 | E6: 80 | F6: =(D6-C6)/(E6-C6) | G6: 2027
A8: Only the yellow 'Current' column is editable — illustrative interim progress, not reported data. Progress is computed as (current − baseline) / (target − baseline), so it reads correctly for carbon intensity (which must fall) and for the two shares (which must rise). Progress here does not set pricing: the number of SPTs met is entered separately on Sheet 3.

Sheet 2. SPT Calibration
A1: SUSTAINABILITY PERFORMANCE TARGET CALIBRATION
A3: KPI | B3: Baseline (2024) | C3: Target year | D3: SPT | E3: Informed by (alignment not established)
A4: Carbon intensity | B4: 310 tCO2e/£m rev | C4: 2028 | D4: <=217 tCO2e/£m rev (-30%) | E4: SBTi near-term criteria
A5: Renewable share | B5: 18% | C5: 2028 | D5: >=60% | E5: UK CCC Sixth Carbon Budget (December 2020)
A6: Supply chain audit | B6: 35% | C6: 2027 | D6: >=80% | E6: LMA SLLP guidance on ambition
A8: Illustrative targets informed by the frameworks named; alignment has not been independently established. SBTi accepts Scope 1+2 intensity targets only when modelled on an approved 1.5C sector pathway applicable to the company, so a chosen percentage is not evidence of alignment.
A11: CARBON INTENSITY GLIDE PATH (linear, baseline → SPT)
A12: Baseline | B12: 310 | C12: ← editable
A13: 2028 SPT | B13: 217
A15: 2024 | B15: 2025 | C15: 2026 | D15: 2027 | E15: 2028
A16: =$B$12+($B$13-$B$12)*0/4 | B16: =$B$12+($B$13-$B$12)*1/4 | C16: =$B$12+($B$13-$B$12)*2/4 | D16: =$B$12+($B$13-$B$12)*3/4 | E16: =$B$12+($B$13-$B$12)*4/4
A17: Change on the prior year (%) — the linear path moves 7.5% of the baseline a year, so this rate rises over time
B18: =B16/A16-1 | C18: =C16/B16-1 | D18: =D16/C16-1 | E18: =E16/D16-1
A19: Equivalent constant annual rate | B19: =($B$13/$B$12)^(1/4)-1
A21: The glide paths are formula-driven from the yellow endpoint cells, so changing a baseline or an SPT moves every interim target. Interim SPTs matter because the ratchet is tested annually, not once at maturity.
A24: RENEWABLE ELECTRICITY SHARE (%) — 2024 → 2028
A25: Baseline | B25: 18 | C25: SPT | D25: 60
A26: 2024 | B26: 2025 | C26: 2026 | D26: 2027 | E26: 2028
A27: =$B$25+($D$25-$B$25)*0/4 | B27: =$B$25+($D$25-$B$25)*1/4 | C27: =$B$25+($D$25-$B$25)*2/4 | D27: =$B$25+($D$25-$B$25)*3/4 | E27: =$B$25+($D$25-$B$25)*4/4
A29: SUPPLY-CHAIN AUDIT COVERAGE (%) — 2024 → 2027
A30: Baseline | B30: 35 | C30: SPT | D30: 80
A31: 2024 | B31: 2025 | C31: 2026 | D31: 2027
A32: =$B$30+($D$30-$B$30)*0/3 | B32: =$B$30+($D$30-$B$30)*1/3 | C32: =$B$30+($D$30-$B$30)*2/3 | D32: =$B$30+($D$30-$B$30)*3/3

Sheet 3. Margin Ratchet
A1: MARGIN RATCHET CALCULATOR (ILLUSTRATIVE)
A2: A revolving facility is rarely fully drawn, and the ratchet applies only to the drawn margin — so the benefit scales with utilisation. The undrawn balance carries a commitment fee, conventionally a fixed share of the margin.
A4: INPUTS
A5: Facility size (£m) | D5: 650
A6: Base margin (bps over SONIA) | D6: 120
A7: SONIA reference rate (%) | D7: 4.25
A8: Utilisation (% of facility drawn) | D8: 1
A9: Commitment fee (% of margin) | D9: 0.35
A10: Full step (bps) — all 3 SPTs met | D10: 7.5
A11: Partial step (bps) — 2 of 3 met | D11: 2.5
A12: Step-up (bps) — 0 met | D12: 7.5
A13: Incremental assurance cost (£m/yr) | D13: 0.1
A14: SPTs met this period (0–3) — scenario input | D14: 3
A16: DERIVED
A17: Drawn balance (£m) | D17: ='3. Margin Ratchet'!$D$5*'3. Margin Ratchet'!$D$8
A18: Undrawn commitment (£m) | D18: ='3. Margin Ratchet'!$D$5*(1-'3. Margin Ratchet'!$D$8)
A19: Commitment fee (bps) | D19: ='3. Margin Ratchet'!$D$6*'3. Margin Ratchet'!$D$9
A20: Margin adjustment (bps) | D20: =IF('3. Margin Ratchet'!$D$14=3,-'3. Margin Ratchet'!$D$10,IF('3. Margin Ratchet'!$D$14=2,-'3. Margin Ratchet'!$D$11,IF('3. Margin Ratchet'!$D$14=1,0,'3. Margin Ratchet'!$D$12)))
A21: Adjusted margin (bps) | D21: ='3. Margin Ratchet'!$D$6+$D$20
A22: All-in rate on drawn (%) | D22: ='3. Margin Ratchet'!$D$7+$D$21/100
A23: Interest on drawn (£m) | D23: =$D$17*$D$22/100
A24: Commitment fee cost (£m) | D24: =$D$18*$D$19/100/100
A25: TOTAL ANNUAL COST (£m) | D25: =$D$23+$D$24
A27: SCENARIO COMPARISON (at the inputs above)
A28: SPTs met | B28: Margin adj (bps) | C28: Margin (bps) | D28: Interest on drawn (£m) | E28: Commitment fee (£m) | F28: Total cost (£m) | G28: vs no adjustment (£k)
A29: 3 | B29: =IF(A29=3,-'3. Margin Ratchet'!$D$10,IF(A29=2,-'3. Margin Ratchet'!$D$11,IF(A29=1,0,'3. Margin Ratchet'!$D$12))) | C29: ='3. Margin Ratchet'!$D$6+B29 | D29: =$D$17*('3. Margin Ratchet'!$D$7+C29/100)/100 | E29: =$D$24 | F29: =D29+E29 | G29: =$D$17*B29/100/100*1000
A30: 2 | B30: =IF(A30=3,-'3. Margin Ratchet'!$D$10,IF(A30=2,-'3. Margin Ratchet'!$D$11,IF(A30=1,0,'3. Margin Ratchet'!$D$12))) | C30: ='3. Margin Ratchet'!$D$6+B30 | D30: =$D$17*('3. Margin Ratchet'!$D$7+C30/100)/100 | E30: =$D$24 | F30: =D30+E30 | G30: =$D$17*B30/100/100*1000
A31: 1 | B31: =IF(A31=3,-'3. Margin Ratchet'!$D$10,IF(A31=2,-'3. Margin Ratchet'!$D$11,IF(A31=1,0,'3. Margin Ratchet'!$D$12))) | C31: ='3. Margin Ratchet'!$D$6+B31 | D31: =$D$17*('3. Margin Ratchet'!$D$7+C31/100)/100 | E31: =$D$24 | F31: =D31+E31 | G31: =$D$17*B31/100/100*1000
A32: 0 | B32: =IF(A32=3,-'3. Margin Ratchet'!$D$10,IF(A32=2,-'3. Margin Ratchet'!$D$11,IF(A32=1,0,'3. Margin Ratchet'!$D$12))) | C32: ='3. Margin Ratchet'!$D$6+B32 | D32: =$D$17*('3. Margin Ratchet'!$D$7+C32/100)/100 | E32: =$D$24 | F32: =D32+E32 | G32: =$D$17*B32/100/100*1000
A34: The commitment fee is identical across scenarios because this structure ratchets only the drawn margin, and it would be charged on an equivalent conventional revolver too. If the fee were also linked to the margin, the effect would fall on the undrawn balance and so depend on utilisation: at 0% drawn it would be the largest part of the benefit.

Sheet 4. Utilisation Sensitivity
A1: RATCHET BENEFIT BY UTILISATION
A2: The headline ratchet saving assumes the facility is fully drawn. It is not a fixed benefit: it is proportional to the drawn balance, while the verification cost that earns it is fixed. This is the table that decides whether an SLL is worth doing on price alone.
A5: Utilisation | B5: Drawn (£m) | C5: Total cost at base margin (£m) | D5: Max annual saving (£k) | E5: Incremental assurance (£k) | F5: Net vs conventional (£k)
A6: 0 | B6: ='3. Margin Ratchet'!$D$5*A6 | C6: =B6*('3. Margin Ratchet'!$D$7+'3. Margin Ratchet'!$D$6/100)/100+('3. Margin Ratchet'!$D$5-B6)*('3. Margin Ratchet'!$D$6*'3. Margin Ratchet'!$D$9)/100/100 | D6: =B6*'3. Margin Ratchet'!$D$10/100/100*1000 | E6: ='3. Margin Ratchet'!$D$13*1000 | F6: =D6-E6
A7: 0.2 | B7: ='3. Margin Ratchet'!$D$5*A7 | C7: =B7*('3. Margin Ratchet'!$D$7+'3. Margin Ratchet'!$D$6/100)/100+('3. Margin Ratchet'!$D$5-B7)*('3. Margin Ratchet'!$D$6*'3. Margin Ratchet'!$D$9)/100/100 | D7: =B7*'3. Margin Ratchet'!$D$10/100/100*1000 | E7: ='3. Margin Ratchet'!$D$13*1000 | F7: =D7-E7
A8: 0.4 | B8: ='3. Margin Ratchet'!$D$5*A8 | C8: =B8*('3. Margin Ratchet'!$D$7+'3. Margin Ratchet'!$D$6/100)/100+('3. Margin Ratchet'!$D$5-B8)*('3. Margin Ratchet'!$D$6*'3. Margin Ratchet'!$D$9)/100/100 | D8: =B8*'3. Margin Ratchet'!$D$10/100/100*1000 | E8: ='3. Margin Ratchet'!$D$13*1000 | F8: =D8-E8
A9: 0.6 | B9: ='3. Margin Ratchet'!$D$5*A9 | C9: =B9*('3. Margin Ratchet'!$D$7+'3. Margin Ratchet'!$D$6/100)/100+('3. Margin Ratchet'!$D$5-B9)*('3. Margin Ratchet'!$D$6*'3. Margin Ratchet'!$D$9)/100/100 | D9: =B9*'3. Margin Ratchet'!$D$10/100/100*1000 | E9: ='3. Margin Ratchet'!$D$13*1000 | F9: =D9-E9
A10: 0.8 | B10: ='3. Margin Ratchet'!$D$5*A10 | C10: =B10*('3. Margin Ratchet'!$D$7+'3. Margin Ratchet'!$D$6/100)/100+('3. Margin Ratchet'!$D$5-B10)*('3. Margin Ratchet'!$D$6*'3. Margin Ratchet'!$D$9)/100/100 | D10: =B10*'3. Margin Ratchet'!$D$10/100/100*1000 | E10: ='3. Margin Ratchet'!$D$13*1000 | F10: =D10-E10
A11: 1 | B11: ='3. Margin Ratchet'!$D$5*A11 | C11: =B11*('3. Margin Ratchet'!$D$7+'3. Margin Ratchet'!$D$6/100)/100+('3. Margin Ratchet'!$D$5-B11)*('3. Margin Ratchet'!$D$6*'3. Margin Ratchet'!$D$9)/100/100 | D11: =B11*'3. Margin Ratchet'!$D$10/100/100*1000 | E11: ='3. Margin Ratchet'!$D$13*1000 | F11: =D11-E11
A13: BREAK-EVEN
A14: Best-case pricing break-even | B14: ='3. Margin Ratchet'!$D$13/('3. Margin Ratchet'!$D$5*'3. Margin Ratchet'!$D$10/100/100) | C14: Below this drawdown the best-case annual saving does not cover the incremental assurance cost, under the model assumptions.
A16: At the default inputs the best-case annual pricing break-even is about 21% utilisation. It assumes every SPT is met, the whole assurance cost is incremental (already-verified reporting can reduce it), only the drawn margin changes, and there are no other incremental costs. The commitment fee is excluded because an equivalent conventional revolver would charge it too. Where a real borrower would operate is a liquidity question this model does not answer.

Sheet 5. Economics & Caveats
A1: INCREMENTAL ECONOMICS VS AN EQUIVALENT CONVENTIONAL REVOLVER
A3: AT THE DEFAULT INPUTS (commitment fee cancels: charged on both)
A4: Measure | B4: Value | C4: Unit | D4: Note
A5: Facility size | B5: ='3. Margin Ratchet'!$D$5 | C5: £m | D5: Committed amount
A6: Assumed utilisation | B6: ='3. Margin Ratchet'!$D$8 | C6: % | D6: Share drawn on average
A7: Best-case annual saving | B7: =$B$5*$B$6*'3. Margin Ratchet'!$D$10/100/100*1000 | C7: £k | D7: All 3 SPTs met, on the drawn balance
A8: Incremental assurance cost | B8: ='3. Margin Ratchet'!$D$13*1000 | C8: £k | D8: Fixed; may be lower where reporting is already verified
A9: Net annual benefit vs conventional | B9: =$B$7-$B$8 | C9: £k | D9: Negative means the feature costs more than it returns
A10: Best-case pricing break-even | B10: ='3. Margin Ratchet'!$D$13/('3. Margin Ratchet'!$D$5*'3. Margin Ratchet'!$D$10/100/100) | C10: % | D10: Drawdown at which best-case saving = assurance cost
A12: WHAT THIS MODEL DELIBERATELY DOES NOT CLAIM
A13: • The ratchet is priced on the drawn margin only. A linked commitment fee would add a benefit on the undrawn balance, largest when least drawn.
A14: • The pricing grid is unweighted: it counts SPTs met, not which ones, so the carbon target can be missed while a partial step-down is earned.
A15: • The SPTs are illustrative; alignment with SBTi, CCC or SLLP benchmarks has not been independently established.
A16: • No discounting: these are single-year figures. Over a five-year facility the saving is roughly five times the annual number, less the verification cost each year.
A17: • Verification cost is a single illustrative input. Real assurance costs vary with scope, and the first year is usually dearer than later ones.
A18: • The two-way ratchet assumes the step-up is genuinely enforced. A step-down-only structure gives the borrower a free option and is the main greenwashing channel the SLLP guidance targets.
A19: • KPI selection, not pricing, is where the real integrity risk sits: a material KPI with an unambitious SPT prices identically to a demanding one in this model.
A21: VERIFICATION & REPORTING
A22: External verifier: an auditor or specialist ESG verifier. Reporting: annual sustainability report plus a loan anniversary compliance letter. Assurance standard: ISAE 3000 / AA1000AS. KPI data sourced from SECR disclosures (energy and carbon) and the REGO certificate registry (renewable share) — both UK statutory or registry-based, so no paid data subscription is required.
A26: All figures illustrative — hypothetical borrower, facility and rates.
